telestream_cloud_flip/__init__.py
telestream_cloud_flip/api_client.py
telestream_cloud_flip/configuration.py
telestream_cloud_flip/exceptions.py
telestream_cloud_flip/rest.py
telestream_cloud_flip/api/__init__.py
telestream_cloud_flip/api/flip_api.py
telestream_cloud_flip/models/__init__.py
telestream_cloud_flip/models/canceled_response.py
telestream_cloud_flip/models/copy_profile_body.py
telestream_cloud_flip/models/count_response.py
telestream_cloud_flip/models/create_encoding_body.py
telestream_cloud_flip/models/create_video_body.py
telestream_cloud_flip/models/deleted_response.py
telestream_cloud_flip/models/encoding.py
telestream_cloud_flip/models/encoding_signed_url.py
telestream_cloud_flip/models/encoding_signed_urls.py
telestream_cloud_flip/models/error.py
telestream_cloud_flip/models/extra_file.py
telestream_cloud_flip/models/factory.py
telestream_cloud_flip/models/paginated_encodings_collection.py
telestream_cloud_flip/models/paginated_factory_collection.py
telestream_cloud_flip/models/paginated_profiles_collection.py
telestream_cloud_flip/models/paginated_video_collection.py
telestream_cloud_flip/models/paginated_workflows_collection.py
telestream_cloud_flip/models/profile.py
telestream_cloud_flip/models/resubmit_video_body.py
telestream_cloud_flip/models/retried_response.py
telestream_cloud_flip/models/signed_video_url.py
telestream_cloud_flip/models/update_encoding_body.py
telestream_cloud_flip/models/video.py
telestream_cloud_flip-2.1.0.dist-info/METADATA
telestream_cloud_flip-2.1.0.dist-info/WHEEL
telestream_cloud_flip-2.1.0.dist-info/top_level.txt
telestream_cloud_flip-2.1.0.dist-info/RECORD
